querymaster/__init__.py
querymaster-0.0.1.dist-info/LICENSE
querymaster-0.0.1.dist-info/METADATA
querymaster-0.0.1.dist-info/WHEEL
querymaster-0.0.1.dist-info/top_level.txt
querymaster-0.0.1.dist-info/RECORD
