Metadata-Version: 2.1
Name: querymaster
Version: 0.0.1
Summary: Query Master enables the use of multiple databases in one place.
Home-page: https://github.com/FileXdb/QueryMaster.git
Author: Sam (AcePic Studio)
Author-email: biswassamrat903@gmail.com
Project-URL: Homepage, https://github.com/FileXdb/QueryMaster.git
Project-URL: Repository, https://github.com/FileXdb/QueryMaster.git
Project-URL: Bug Tracker, https://github.com/FileXdb/QueryMaster.git/issues
Classifier: Development Status :: 4 - Beta
Classifier: Programming Language :: Python :: 3
Classifier: License :: OSI Approved :: MIT License
Classifier: Operating System :: OS Independent
Requires-Python: >=3.7
License-File: LICENSE
